{"expand": "renderedFields,names,schema,operations,editmeta,changelog,versionedRepresentations", "id": "12970130", "self": "https://issues.apache.org/jira/rest/api/2/issue/12970130", "key": "MAPREDUCE-6697", "fields": {"fixVersions": [{"self": "https://issues.apache.org/jira/rest/api/2/version/12334217", "id": "12334217", "description": "2.9.0 release", "name": "2.9.0", "archived": false, "released": true, "releaseDate": "2017-11-17"}, {"self": "https://issues.apache.org/jira/rest/api/2/version/12335547", "id": "12335547", "description": "2.7.4 release", "name": "2.7.4", "archived": false, "released": true, "releaseDate": "2017-08-04"}, {"self": "https://issues.apache.org/jira/rest/api/2/version/12339181", "id": "12339181", "name": "3.0.0-alpha4", "archived": false, "released": true, "releaseDate": "2017-07-07"}, {"self": "https://issues.apache.org/jira/rest/api/2/version/12340355", "id": "12340355", "name": "2.8.2", "archived": false, "released": true, "releaseDate": "2017-10-24"}], "resolution": {"self": "https://issues.apache.org/jira/rest/api/2/resolution/1", "id": "1", "description": "A fix for this issue is checked into the tree and tested.", "name": "Fixed"}, "customfield_12312322": null, "customfield_12312323": null, "customfield_12310420": "9223372036854775807", "customfield_12312320": null, "customfield_12312321": null, "customfield_12312328": null, "customfield_12312329": null, "customfield_12312326": null, "customfield_12310300": null, "customfield_12312327": null, "customfield_12312324": null, "customfield_12312720": null, "customfield_12312325": null, "lastViewed": null, "priority": {"self": "https://issues.apache.org/jira/rest/api/2/priority/3", "iconUrl": "https://issues.apache.org/jira/images/icons/priorities/major.svg", "name": "Major", "id": "3"}, "labels": [], "customfield_12312333": null, "customfield_12312334": null, "customfield_12313422": "false", "customfield_12310310": "3.0", "customfield_12312331": null, "customfield_12312332": null, "aggregatetimeoriginalestimate": null, "timeestimate": null, "customfield_12312330": null, "versions": [{"self": "https://issues.apache.org/jira/rest/api/2/version/12327586", "id": "12327586", "description": "2.7.0 release", "name": "2.7.0", "archived": false, "released": true, "releaseDate": "2015-04-20"}], "customfield_12311120": null, "customfield_12313826": null, "issuelinks": [{"id": "12466619", "self": "https://issues.apache.org/jira/rest/api/2/issueLink/12466619", "type": {"id": "10030", "name": "Reference", "inward": "is related to", "outward": "relates to", "self": "https://issues.apache.org/jira/rest/api/2/issueLinkType/10030"}, "outwardIssue": {"id": "12673770", "key": "MAPREDUCE-5583", "self": "https://issues.apache.org/jira/rest/api/2/issue/12673770", "fields": {"summary": "Ability to limit running map and reduce tasks", "status": {"self": "https://issues.apache.org/jira/rest/api/2/status/6", "description": "The issue is considered finished, the resolution is correct. Issues which are not closed can be reopened.", "iconUrl": "https://issues.apache.org/jira/images/icons/statuses/closed.png", "name": "Closed", "id": "6", "statusCategory": {"self": "https://issues.apache.org/jira/rest/api/2/statuscategory/3", "id": 3, "key": "done", "colorName": "green", "name": "Done"}}, "priority": {"self": "https://issues.apache.org/jira/rest/api/2/priority/3", "iconUrl": "https://issues.apache.org/jira/images/icons/priorities/major.svg", "name": "Major", "id": "3"}, "issuetype": {"self": "https://issues.apache.org/jira/rest/api/2/issuetype/4", "id": "4", "description": "An improvement or enhancement to an existing feature or task.", "iconUrl": "https://issues.apache.org/jira/secure/viewavatar?size=xsmall&avatarId=21140&avatarType=issuetype", "name": "Improvement", "subtask": false, "avatarId": 21140}}}}], "customfield_12312339": null, "customfield_12313825": null, "assignee": {"self": "https://issues.apache.org/jira/rest/api/2/user?username=nroberts", "name": "nroberts", "key": "nroberts", "avatarUrls": {"48x48": "https://issues.apache.org/jira/secure/useravatar?avatarId=10452", "24x24": "https://issues.apache.org/jira/secure/useravatar?size=small&avatarId=10452", "16x16": "https://issues.apache.org/jira/secure/useravatar?size=xsmall&avatarId=10452", "32x32": "https://issues.apache.org/jira/secure/useravatar?size=medium&avatarId=10452"}, "displayName": "Nathan Roberts", "active": true, "timeZone": "America/Chicago"}, "customfield_12312337": null, "customfield_12313823": null, "customfield_12312338": null, "customfield_12311920": null, "customfield_12313822": null, "customfield_12312335": null, "customfield_12313821": null, "customfield_12312336": null, "customfield_12313820": null, "status": {"self": "https://issues.apache.org/jira/rest/api/2/status/5", "description": "A resolution has been taken, and it is awaiting verification by reporter. From here issues are either reopened, or are closed.", "iconUrl": "https://issues.apache.org/jira/images/icons/statuses/resolved.png", "name": "Resolved", "id": "5", "statusCategory": {"self": "https://issues.apache.org/jira/rest/api/2/statuscategory/3", "id": 3, "key": "done", "colorName": "green", "name": "Done"}}, "components": [{"self": "https://issues.apache.org/jira/rest/api/2/component/12314301", "id": "12314301", "name": "mrv2", "description": "MR-279: Map Reduce Next."}], "archiveddate": null, "customfield_12312026": null, "customfield_12312023": null, "customfield_12312024": null, "aggregatetimeestimate": null, "customfield_12312022": null, "customfield_12310921": null, "customfield_12310920": "9223372036854775807", "customfield_12312823": null, "creator": {"self": "https://issues.apache.org/jira/rest/api/2/user?username=jlowe", "name": "jlowe", "key": "jlowe", "avatarUrls": {"48x48": "https://issues.apache.org/jira/secure/useravatar?avatarId=10452", "24x24": "https://issues.apache.org/jira/secure/useravatar?size=small&avatarId=10452", "16x16": "https://issues.apache.org/jira/secure/useravatar?size=xsmall&avatarId=10452", "32x32": "https://issues.apache.org/jira/secure/useravatar?size=medium&avatarId=10452"}, "displayName": "Jason Darrell Lowe", "active": true, "timeZone": "America/Chicago"}, "subtasks": [], "reporter": {"self": "https://issues.apache.org/jira/rest/api/2/user?username=jlowe", "name": "jlowe", "key": "jlowe", "avatarUrls": {"48x48": "https://issues.apache.org/jira/secure/useravatar?avatarId=10452", "24x24": "https://issues.apache.org/jira/secure/useravatar?size=small&avatarId=10452", "16x16": "https://issues.apache.org/jira/secure/useravatar?size=xsmall&avatarId=10452", "32x32": "https://issues.apache.org/jira/secure/useravatar?size=medium&avatarId=10452"}, "displayName": "Jason Darrell Lowe", "active": true, "timeZone": "America/Chicago"}, "aggregateprogress": {"progress": 0, "total": 0}, "customfield_12313520": null, "customfield_12310250": null, "progress": {"progress": 0, "total": 0}, "customfield_12313924": null, "votes": {"self": "https://issues.apache.org/jira/rest/api/2/issue/MAPREDUCE-6697/votes", "votes": 0, "hasVoted": false}, "worklog": {"startAt": 0, "maxResults": 20, "total": 0, "worklogs": []}, "archivedby": null, "customfield_12313920": null, "issuetype": {"self": "https://issues.apache.org/jira/rest/api/2/issuetype/1", "id": "1", "description": "A problem which impairs or prevents the functions of the product.", "iconUrl": "https://issues.apache.org/jira/secure/viewavatar?size=xsmall&avatarId=21133&avatarType=issuetype", "name": "Bug", "subtask": false, "avatarId": 21133}, "timespent": null, "customfield_12314020": "{summaryBean=com.atlassian.jira.plugin.devstatus.rest.SummaryBean@4c823b71[summary={pullrequest=com.atlassian.jira.plugin.devstatus.rest.SummaryItemBean@368f0243[overall=PullRequestOverallBean{stateCount=0, state='OPEN', details=PullRequestOverallDetails{openCount=0, mergedCount=0, declinedCount=0}},byInstanceType={}], build=com.atlassian.jira.plugin.devstatus.rest.SummaryItemBean@610ba5c8[overall=com.atlassian.jira.plugin.devstatus.summary.beans.BuildOverallBean@2f583eb0[failedBuildCount=0,successfulBuildCount=0,unknownBuildCount=0,count=0,lastUpdated=<null>,lastUpdatedTimestamp=<null>],byInstanceType={}], review=com.atlassian.jira.plugin.devstatus.rest.SummaryItemBean@1e9f79ad[overall=com.atlassian.jira.plugin.devstatus.summary.beans.ReviewsOverallBean@58123175[stateCount=0,state=<null>,dueDate=<null>,overDue=false,count=0,lastUpdated=<null>,lastUpdatedTimestamp=<null>],byInstanceType={}], deployment-environment=com.atlassian.jira.plugin.devstatus.rest.SummaryItemBean@648bea5a[overall=com.atlassian.jira.plugin.devstatus.summary.beans.DeploymentOverallBean@ac8f5c5[topEnvironments=[],showProjects=false,successfulCount=0,count=0,lastUpdated=<null>,lastUpdatedTimestamp=<null>],byInstanceType={}], repository=com.atlassian.jira.plugin.devstatus.rest.SummaryItemBean@6fffa720[overall=com.atlassian.jira.plugin.devstatus.summary.beans.CommitOverallBean@262fba33[count=0,lastUpdated=<null>,lastUpdatedTimestamp=<null>],byInstanceType={}], branch=com.atlassian.jira.plugin.devstatus.rest.SummaryItemBean@1dcd4d96[overall=com.atlassian.jira.plugin.devstatus.summary.beans.BranchOverallBean@5066e537[count=0,lastUpdated=<null>,lastUpdatedTimestamp=<null>],byInstanceType={}]},errors=[],configErrors=[]], devSummaryJson={\"cachedValue\":{\"errors\":[],\"configErrors\":[],\"summary\":{\"pullrequest\":{\"overall\":{\"count\":0,\"lastUpdated\":null,\"stateCount\":0,\"state\":\"OPEN\",\"details\":{\"openCount\":0,\"mergedCount\":0,\"declinedCount\":0,\"total\":0},\"open\":true},\"byInstanceType\":{}},\"build\":{\"overall\":{\"count\":0,\"lastUpdated\":null,\"failedBuildCount\":0,\"successfulBuildCount\":0,\"unknownBuildCount\":0},\"byInstanceType\":{}},\"review\":{\"overall\":{\"count\":0,\"lastUpdated\":null,\"stateCount\":0,\"state\":null,\"dueDate\":null,\"overDue\":false,\"completed\":false},\"byInstanceType\":{}},\"deployment-environment\":{\"overall\":{\"count\":0,\"lastUpdated\":null,\"topEnvironments\":[],\"showProjects\":false,\"successfulCount\":0},\"byInstanceType\":{}},\"repository\":{\"overall\":{\"count\":0,\"lastUpdated\":null},\"byInstanceType\":{}},\"branch\":{\"overall\":{\"count\":0,\"lastUpdated\":null},\"byInstanceType\":{}}}},\"isStale\":false}}", "customfield_12314141": null, "customfield_12314140": null, "project": {"self": "https://issues.apache.org/jira/rest/api/2/project/12310941", "id": "12310941", "key": "MAPREDUCE", "name": "Hadoop Map/Reduce", "projectTypeKey": "software", "avatarUrls": {"48x48": "https://issues.apache.org/jira/secure/projectavatar?pid=12310941&avatarId=10096", "24x24": "https://issues.apache.org/jira/secure/projectavatar?size=small&pid=12310941&avatarId=10096", "16x16": "https://issues.apache.org/jira/secure/projectavatar?size=xsmall&pid=12310941&avatarId=10096", "32x32": "https://issues.apache.org/jira/secure/projectavatar?size=medium&pid=12310941&avatarId=10096"}, "projectCategory": {"self": "https://issues.apache.org/jira/rest/api/2/projectCategory/10292", "id": "10292", "description": "Scalable Distributed Computing", "name": "Hadoop"}}, "aggregatetimespent": null, "customfield_12312520": null, "customfield_12312521": "Thu Jul 13 21:40:29 UTC 2017", "customfield_12314422": null, "customfield_12314421": null, "customfield_12314146": null, "customfield_12314420": null, "customfield_12314145": null, "customfield_12314144": null, "customfield_12314143": null, "resolutiondate": "2017-07-13T21:40:29.263+0000", "workratio": -1, "customfield_12312923": null, "customfield_12312920": null, "customfield_12312921": null, "watches": {"self": "https://issues.apache.org/jira/rest/api/2/issue/MAPREDUCE-6697/watchers", "watchCount": 14, "isWatching": false}, "created": "2016-05-16T19:52:54.446+0000", "customfield_12310192": null, "customfield_12310191": [{"self": "https://issues.apache.org/jira/rest/api/2/customFieldOption/10343", "value": "Reviewed", "id": "10343", "disabled": false}], "customfield_12310230": null, "updated": "2017-07-13T21:40:29.324+0000", "timeoriginalestimate": null, "description": "The concurrent task limit feature should only adjust the ANY portion of the AM heartbeat ask when a limit is truly necessary, otherwise extraneous containers could be allocated by the RM to the AM adding some overhead to both.  Specifying a concurrent task limit that is beyond the total number of tasks in the job should be the same as asking for no limit.", "customfield_10010": null, "timetracking": {}, "customfield_12314523": null, "customfield_12314127": null, "customfield_12314522": null, "customfield_12314126": null, "customfield_12314521": null, "customfield_12314125": null, "customfield_12310320": [{"self": "https://issues.apache.org/jira/rest/api/2/version/12335547", "id": "12335547", "description": "2.7.4 release", "name": "2.7.4", "archived": false, "released": true, "releaseDate": "2017-08-04"}], "customfield_12314520": null, "customfield_12314124": null, "customfield_12312340": null, "attachment": [{"self": "https://issues.apache.org/jira/rest/api/2/attachment/12876967", "id": "12876967", "filename": "MAPREDUCE-6697-branch-2.7.001.patch", "author": {"self": "https://issues.apache.org/jira/rest/api/2/user?username=shv", "name": "shv", "key": "shv", "avatarUrls": {"48x48": "https://issues.apache.org/jira/secure/useravatar?avatarId=10452", "24x24": "https://issues.apache.org/jira/secure/useravatar?size=small&avatarId=10452", "16x16": "https://issues.apache.org/jira/secure/useravatar?size=xsmall&avatarId=10452", "32x32": "https://issues.apache.org/jira/secure/useravatar?size=medium&avatarId=10452"}, "displayName": "Konstantin Shvachko", "active": true, "timeZone": "America/Los_Angeles"}, "created": "2017-07-12T22:37:56.150+0000", "size": 7105, "mimeType": "application/force-download", "content": "https://issues.apache.org/jira/secure/attachment/12876967/MAPREDUCE-6697-branch-2.7.001.patch"}, {"self": "https://issues.apache.org/jira/rest/api/2/attachment/12876863", "id": "12876863", "filename": "MAPREDUCE-6697-branch-2.8.001.patch", "author": {"self": "https://issues.apache.org/jira/rest/api/2/user?username=nroberts", "name": "nroberts", "key": "nroberts", "avatarUrls": {"48x48": "https://issues.apache.org/jira/secure/useravatar?avatarId=10452", "24x24": "https://issues.apache.org/jira/secure/useravatar?size=small&avatarId=10452", "16x16": "https://issues.apache.org/jira/secure/useravatar?size=xsmall&avatarId=10452", "32x32": "https://issues.apache.org/jira/secure/useravatar?size=medium&avatarId=10452"}, "displayName": "Nathan Roberts", "active": true, "timeZone": "America/Chicago"}, "created": "2017-07-12T15:00:14.512+0000", "size": 7105, "mimeType": "text/plain", "content": "https://issues.apache.org/jira/secure/attachment/12876863/MAPREDUCE-6697-branch-2.8.001.patch"}, {"self": "https://issues.apache.org/jira/rest/api/2/attachment/12810463", "id": "12810463", "filename": "MAPREDUCE-6697-v1.patch", "author": {"self": "https://issues.apache.org/jira/rest/api/2/user?username=nroberts", "name": "nroberts", "key": "nroberts", "avatarUrls": {"48x48": "https://issues.apache.org/jira/secure/useravatar?avatarId=10452", "24x24": "https://issues.apache.org/jira/secure/useravatar?size=small&avatarId=10452", "16x16": "https://issues.apache.org/jira/secure/useravatar?size=xsmall&avatarId=10452", "32x32": "https://issues.apache.org/jira/secure/useravatar?size=medium&avatarId=10452"}, "displayName": "Nathan Roberts", "active": true, "timeZone": "America/Chicago"}, "created": "2016-06-14T16:27:50.981+0000", "size": 7094, "mimeType": "text/x-patch", "content": "https://issues.apache.org/jira/secure/attachment/12810463/MAPREDUCE-6697-v1.patch"}], "customfield_12314123": null, "customfield_12312341": null, "customfield_12312220": null, "customfield_12314122": null, "customfield_12314121": null, "customfield_12314120": null, "customfield_12314129": null, "customfield_12314524": null, "customfield_12314128": null, "summary": "Concurrent task limits should only be applied when necessary", "customfield_12314130": null, "customfield_12310291": null, "customfield_12310290": null, "customfield_12311024": null, "customfield_12314138": null, "customfield_12314137": null, "environment": null, "customfield_12314136": null, "customfield_12314135": null, "customfield_12311020": null, "customfield_12314134": null, "duedate": null, "customfield_12314132": null, "customfield_12314131": null, "comment": {"comments": [{"self": "https://issues.apache.org/jira/rest/api/2/issue/12970130/comment/15329806", "id": "15329806", "author": {"self": "https://issues.apache.org/jira/rest/api/2/user?username=nroberts", "name": "nroberts", "key": "nroberts", "avatarUrls": {"48x48": "https://issues.apache.org/jira/secure/useravatar?avatarId=10452", "24x24": "https://issues.apache.org/jira/secure/useravatar?size=small&avatarId=10452", "16x16": "https://issues.apache.org/jira/secure/useravatar?size=xsmall&avatarId=10452", "32x32": "https://issues.apache.org/jira/secure/useravatar?size=medium&avatarId=10452"}, "displayName": "Nathan Roberts", "active": true, "timeZone": "America/Chicago"}, "body": "Attaching patch. Ideally it wouldn't call getTotalMaps/Reduces() on each heartbeat but it keeps the patch small and it looks to be a pretty cheap call.\n", "updateAuthor": {"self": "https://issues.apache.org/jira/rest/api/2/user?username=nroberts", "name": "nroberts", "key": "nroberts", "avatarUrls": {"48x48": "https://issues.apache.org/jira/secure/useravatar?avatarId=10452", "24x24": "https://issues.apache.org/jira/secure/useravatar?size=small&avatarId=10452", "16x16": "https://issues.apache.org/jira/secure/useravatar?size=xsmall&avatarId=10452", "32x32": "https://issues.apache.org/jira/secure/useravatar?size=medium&avatarId=10452"}, "displayName": "Nathan Roberts", "active": true, "timeZone": "America/Chicago"}, "created": "2016-06-14T16:27:50.985+0000", "updated": "2016-06-14T16:27:50.985+0000"}, {"self": "https://issues.apache.org/jira/rest/api/2/issue/12970130/comment/15329896", "id": "15329896", "author": {"self": "https://issues.apache.org/jira/rest/api/2/user?username=hadoopqa", "name": "hadoopqa", "key": "hadoopqa", "avatarUrls": {"48x48": "https://issues.apache.org/jira/secure/useravatar?ownerId=hadoopqa&avatarId=10393", "24x24": "https://issues.apache.org/jira/secure/useravatar?size=small&ownerId=hadoopqa&avatarId=10393", "16x16": "https://issues.apache.org/jira/secure/useravatar?size=xsmall&ownerId=hadoopqa&avatarId=10393", "32x32": "https://issues.apache.org/jira/secure/useravatar?size=medium&ownerId=hadoopqa&avatarId=10393"}, "displayName": "Hadoop QA", "active": true, "timeZone": "Etc/UTC"}, "body": "| (x) *{color:red}-1 overall{color}* |\n\\\\\n\\\\\n|| Vote || Subsystem || Runtime || Comment ||\n| {color:blue}0{color} | {color:blue} reexec {color} | {color:blue} 0m 18s {color} | {color:blue} Docker mode activated. {color} |\n| {color:green}+1{color} | {color:green} @author {color} | {color:green} 0m 0s {color} | {color:green} The patch does not contain any @author tags. {color} |\n| {color:green}+1{color} | {color:green} test4tests {color} | {color:green} 0m 0s {color} | {color:green} The patch appears to include 1 new or modified test files. {color} |\n| {color:green}+1{color} | {color:green} mvninstall {color} | {color:green} 6m 31s {color} | {color:green} trunk passed {color} |\n| {color:green}+1{color} | {color:green} compile {color} | {color:green} 0m 19s {color} | {color:green} trunk passed {color} |\n| {color:green}+1{color} | {color:green} checkstyle {color} | {color:green} 0m 18s {color} | {color:green} trunk passed {color} |\n| {color:green}+1{color} | {color:green} mvnsite {color} | {color:green} 0m 23s {color} | {color:green} trunk passed {color} |\n| {color:green}+1{color} | {color:green} mvneclipse {color} | {color:green} 0m 12s {color} | {color:green} trunk passed {color} |\n| {color:green}+1{color} | {color:green} findbugs {color} | {color:green} 0m 33s {color} | {color:green} trunk passed {color} |\n| {color:green}+1{color} | {color:green} javadoc {color} | {color:green} 0m 14s {color} | {color:green} trunk passed {color} |\n| {color:green}+1{color} | {color:green} mvninstall {color} | {color:green} 0m 19s {color} | {color:green} the patch passed {color} |\n| {color:green}+1{color} | {color:green} compile {color} | {color:green} 0m 16s {color} | {color:green} the patch passed {color} |\n| {color:green}+1{color} | {color:green} javac {color} | {color:green} 0m 16s {color} | {color:green} the patch passed {color} |\n| {color:red}-1{color} | {color:red} checkstyle {color} | {color:red} 0m 15s {color} | {color:red} hadoop-mapreduce-project/hadoop-mapreduce-client/hadoop-mapreduce-client-app: The patch generated 8 new + 225 unchanged - 0 fixed = 233 total (was 225) {color} |\n| {color:green}+1{color} | {color:green} mvnsite {color} | {color:green} 0m 22s {color} | {color:green} the patch passed {color} |\n| {color:green}+1{color} | {color:green} mvneclipse {color} | {color:green} 0m 8s {color} | {color:green} the patch passed {color} |\n| {color:green}+1{color} | {color:green} whitespace {color} | {color:green} 0m 1s {color} | {color:green} The patch has no whitespace issues. {color} |\n| {color:green}+1{color} | {color:green} findbugs {color} | {color:green} 0m 39s {color} | {color:green} the patch passed {color} |\n| {color:green}+1{color} | {color:green} javadoc {color} | {color:green} 0m 12s {color} | {color:green} the patch passed {color} |\n| {color:green}+1{color} | {color:green} unit {color} | {color:green} 8m 50s {color} | {color:green} hadoop-mapreduce-client-app in the patch passed. {color} |\n| {color:green}+1{color} | {color:green} asflicense {color} | {color:green} 0m 18s {color} | {color:green} The patch does not generate ASF License warnings. {color} |\n| {color:black}{color} | {color:black} {color} | {color:black} 20m 44s {color} | {color:black} {color} |\n\\\\\n\\\\\n|| Subsystem || Report/Notes ||\n| Docker |  Image:yetus/hadoop:2c91fd8 |\n| JIRA Patch URL | https://issues.apache.org/jira/secure/attachment/12810463/MAPREDUCE-6697-v1.patch |\n| JIRA Issue | MAPREDUCE-6697 |\n| Optional Tests |  asflicense  compile  javac  javadoc  mvninstall  mvnsite  unit  findbugs  checkstyle  |\n| uname | Linux 8a837cb6fcc8 3.13.0-36-lowlatency #63-Ubuntu SMP PREEMPT Wed Sep 3 21:56:12 UTC 2014 x86_64 x86_64 x86_64 GNU/Linux |\n| Build tool | maven |\n| Personality | /testptch/hadoop/patchprocess/precommit/personality/provided.sh |\n| git revision | trunk / 8e8cb4c |\n| Default Java | 1.8.0_91 |\n| findbugs | v3.0.0 |\n| checkstyle | https://builds.apache.org/job/PreCommit-MAPREDUCE-Build/6556/artifact/patchprocess/diff-checkstyle-hadoop-mapreduce-project_hadoop-mapreduce-client_hadoop-mapreduce-client-app.txt |\n|  Test Results | https://builds.apache.org/job/PreCommit-MAPREDUCE-Build/6556/testReport/ |\n| modules | C: hadoop-mapreduce-project/hadoop-mapreduce-client/hadoop-mapreduce-client-app U: hadoop-mapreduce-project/hadoop-mapreduce-client/hadoop-mapreduce-client-app |\n| Console output | https://builds.apache.org/job/PreCommit-MAPREDUCE-Build/6556/console |\n| Powered by | Apache Yetus 0.3.0   http://yetus.apache.org |\n\n\nThis message was automatically generated.\n\n", "updateAuthor": {"self": "https://issues.apache.org/jira/rest/api/2/user?username=hadoopqa", "name": "hadoopqa", "key": "hadoopqa", "avatarUrls": {"48x48": "https://issues.apache.org/jira/secure/useravatar?ownerId=hadoopqa&avatarId=10393", "24x24": "https://issues.apache.org/jira/secure/useravatar?size=small&ownerId=hadoopqa&avatarId=10393", "16x16": "https://issues.apache.org/jira/secure/useravatar?size=xsmall&ownerId=hadoopqa&avatarId=10393", "32x32": "https://issues.apache.org/jira/secure/useravatar?size=medium&ownerId=hadoopqa&avatarId=10393"}, "displayName": "Hadoop QA", "active": true, "timeZone": "Etc/UTC"}, "created": "2016-06-14T17:00:03.126+0000", "updated": "2016-06-14T17:00:03.126+0000"}, {"self": "https://issues.apache.org/jira/rest/api/2/issue/12970130/comment/16046378", "id": "16046378", "author": {"self": "https://issues.apache.org/jira/rest/api/2/user?username=aajisaka", "name": "aajisaka", "key": "ajisakaa", "avatarUrls": {"48x48": "https://issues.apache.org/jira/secure/useravatar?ownerId=ajisakaa&avatarId=17238", "24x24": "https://issues.apache.org/jira/secure/useravatar?size=small&ownerId=ajisakaa&avatarId=17238", "16x16": "https://issues.apache.org/jira/secure/useravatar?size=xsmall&ownerId=ajisakaa&avatarId=17238", "32x32": "https://issues.apache.org/jira/secure/useravatar?size=medium&ownerId=ajisakaa&avatarId=17238"}, "displayName": "Akira Ajisaka", "active": true, "timeZone": "Asia/Tokyo"}, "body": "Mostly looks good to me. I have one question in the test code:\n{code}\n    allocator.schedule();\n    allocator.schedule();\n    allocator.schedule();\n{code}\nwhy the method is called 3 times?", "updateAuthor": {"self": "https://issues.apache.org/jira/rest/api/2/user?username=aajisaka", "name": "aajisaka", "key": "ajisakaa", "avatarUrls": {"48x48": "https://issues.apache.org/jira/secure/useravatar?ownerId=ajisakaa&avatarId=17238", "24x24": "https://issues.apache.org/jira/secure/useravatar?size=small&ownerId=ajisakaa&avatarId=17238", "16x16": "https://issues.apache.org/jira/secure/useravatar?size=xsmall&ownerId=ajisakaa&avatarId=17238", "32x32": "https://issues.apache.org/jira/secure/useravatar?size=medium&ownerId=ajisakaa&avatarId=17238"}, "displayName": "Akira Ajisaka", "active": true, "timeZone": "Asia/Tokyo"}, "created": "2017-06-12T09:34:16.141+0000", "updated": "2017-06-12T09:34:16.141+0000"}, {"self": "https://issues.apache.org/jira/rest/api/2/issue/12970130/comment/16046404", "id": "16046404", "author": {"self": "https://issues.apache.org/jira/rest/api/2/user?username=hadoopqa", "name": "hadoopqa", "key": "hadoopqa", "avatarUrls": {"48x48": "https://issues.apache.org/jira/secure/useravatar?ownerId=hadoopqa&avatarId=10393", "24x24": "https://issues.apache.org/jira/secure/useravatar?size=small&ownerId=hadoopqa&avatarId=10393", "16x16": "https://issues.apache.org/jira/secure/useravatar?size=xsmall&ownerId=hadoopqa&avatarId=10393", "32x32": "https://issues.apache.org/jira/secure/useravatar?size=medium&ownerId=hadoopqa&avatarId=10393"}, "displayName": "Hadoop QA", "active": true, "timeZone": "Etc/UTC"}, "body": "| (/) *{color:green}+1 overall{color}* |\n\\\\\n\\\\\n|| Vote || Subsystem || Runtime || Comment ||\n| {color:blue}0{color} | {color:blue} reexec {color} | {color:blue} 0m 13s {color} | {color:blue} Docker mode activated. {color} |\n| {color:green}+1{color} | {color:green} @author {color} | {color:green} 0m 0s {color} | {color:green} The patch does not contain any @author tags. {color} |\n| {color:green}+1{color} | {color:green} test4tests {color} | {color:green} 0m 0s {color} | {color:green} The patch appears to include 1 new or modified test files. {color} |\n| {color:green}+1{color} | {color:green} mvninstall {color} | {color:green} 12m 31s {color} | {color:green} trunk passed {color} |\n| {color:green}+1{color} | {color:green} compile {color} | {color:green} 0m 22s {color} | {color:green} trunk passed {color} |\n| {color:green}+1{color} | {color:green} checkstyle {color} | {color:green} 0m 13s {color} | {color:green} trunk passed {color} |\n| {color:green}+1{color} | {color:green} mvnsite {color} | {color:green} 0m 23s {color} | {color:green} trunk passed {color} |\n| {color:green}+1{color} | {color:green} mvneclipse {color} | {color:green} 0m 15s {color} | {color:green} trunk passed {color} |\n| {color:green}+1{color} | {color:green} findbugs {color} | {color:green} 0m 34s {color} | {color:green} trunk passed {color} |\n| {color:green}+1{color} | {color:green} javadoc {color} | {color:green} 0m 13s {color} | {color:green} trunk passed {color} |\n| {color:green}+1{color} | {color:green} mvninstall {color} | {color:green} 0m 20s {color} | {color:green} the patch passed {color} |\n| {color:green}+1{color} | {color:green} compile {color} | {color:green} 0m 19s {color} | {color:green} the patch passed {color} |\n| {color:green}+1{color} | {color:green} javac {color} | {color:green} 0m 19s {color} | {color:green} the patch passed {color} |\n| {color:green}+1{color} | {color:green} checkstyle {color} | {color:green} 0m 11s {color} | {color:green} the patch passed {color} |\n| {color:green}+1{color} | {color:green} mvnsite {color} | {color:green} 0m 20s {color} | {color:green} the patch passed {color} |\n| {color:green}+1{color} | {color:green} mvneclipse {color} | {color:green} 0m 14s {color} | {color:green} the patch passed {color} |\n| {color:green}+1{color} | {color:green} whitespace {color} | {color:green} 0m 0s {color} | {color:green} The patch has no whitespace issues. {color} |\n| {color:green}+1{color} | {color:green} findbugs {color} | {color:green} 0m 39s {color} | {color:green} the patch passed {color} |\n| {color:green}+1{color} | {color:green} javadoc {color} | {color:green} 0m 10s {color} | {color:green} the patch passed {color} |\n| {color:green}+1{color} | {color:green} unit {color} | {color:green} 9m 0s {color} | {color:green} hadoop-mapreduce-client-app in the patch passed. {color} |\n| {color:green}+1{color} | {color:green} asflicense {color} | {color:green} 0m 17s {color} | {color:green} The patch does not generate ASF License warnings. {color} |\n| {color:black}{color} | {color:black} {color} | {color:black} 26m 49s {color} | {color:black} {color} |\n\\\\\n\\\\\n|| Subsystem || Report/Notes ||\n| Docker |  Image:yetus/hadoop:14b5c93 |\n| JIRA Patch URL | https://issues.apache.org/jira/secure/attachment/12810463/MAPREDUCE-6697-v1.patch |\n| JIRA Issue | MAPREDUCE-6697 |\n| Optional Tests |  asflicense  compile  javac  javadoc  mvninstall  mvnsite  unit  findbugs  checkstyle  |\n| uname | Linux cd92358638a3 4.4.0-43-generic #63-Ubuntu SMP Wed Oct 12 13:48:03 UTC 2016 x86_64 x86_64 x86_64 GNU/Linux |\n| Build tool | maven |\n| Personality | /testptch/hadoop/patchprocess/precommit/personality/provided.sh |\n| git revision | trunk / e86eef9 |\n| Default Java | 1.8.0_131 |\n| findbugs | v3.1.0-RC1 |\n|  Test Results | https://builds.apache.org/job/PreCommit-MAPREDUCE-Build/6991/testReport/ |\n| modules | C: hadoop-mapreduce-project/hadoop-mapreduce-client/hadoop-mapreduce-client-app U: hadoop-mapreduce-project/hadoop-mapreduce-client/hadoop-mapreduce-client-app |\n| Console output | https://builds.apache.org/job/PreCommit-MAPREDUCE-Build/6991/console |\n| Powered by | Apache Yetus 0.3.0   http://yetus.apache.org |\n\n\nThis message was automatically generated.\n\n", "updateAuthor": {"self": "https://issues.apache.org/jira/rest/api/2/user?username=hadoopqa", "name": "hadoopqa", "key": "hadoopqa", "avatarUrls": {"48x48": "https://issues.apache.org/jira/secure/useravatar?ownerId=hadoopqa&avatarId=10393", "24x24": "https://issues.apache.org/jira/secure/useravatar?size=small&ownerId=hadoopqa&avatarId=10393", "16x16": "https://issues.apache.org/jira/secure/useravatar?size=xsmall&ownerId=hadoopqa&avatarId=10393", "32x32": "https://issues.apache.org/jira/secure/useravatar?size=medium&ownerId=hadoopqa&avatarId=10393"}, "displayName": "Hadoop QA", "active": true, "timeZone": "Etc/UTC"}, "created": "2017-06-12T09:59:58.030+0000", "updated": "2017-06-12T09:59:58.030+0000"}, {"self": "https://issues.apache.org/jira/rest/api/2/issue/12970130/comment/16046409", "id": "16046409", "author": {"self": "https://issues.apache.org/jira/rest/api/2/user?username=hadoopqa", "name": "hadoopqa", "key": "hadoopqa", "avatarUrls": {"48x48": "https://issues.apache.org/jira/secure/useravatar?ownerId=hadoopqa&avatarId=10393", "24x24": "https://issues.apache.org/jira/secure/useravatar?size=small&ownerId=hadoopqa&avatarId=10393", "16x16": "https://issues.apache.org/jira/secure/useravatar?size=xsmall&ownerId=hadoopqa&avatarId=10393", "32x32": "https://issues.apache.org/jira/secure/useravatar?size=medium&ownerId=hadoopqa&avatarId=10393"}, "displayName": "Hadoop QA", "active": true, "timeZone": "Etc/UTC"}, "body": "| (/) *{color:green}+1 overall{color}* |\n\\\\\n\\\\\n|| Vote || Subsystem || Runtime || Comment ||\n| {color:blue}0{color} | {color:blue} reexec {color} | {color:blue} 0m 15s {color} | {color:blue} Docker mode activated. {color} |\n| {color:green}+1{color} | {color:green} @author {color} | {color:green} 0m 1s {color} | {color:green} The patch does not contain any @author tags. {color} |\n| {color:green}+1{color} | {color:green} test4tests {color} | {color:green} 0m 0s {color} | {color:green} The patch appears to include 1 new or modified test files. {color} |\n| {color:green}+1{color} | {color:green} mvninstall {color} | {color:green} 12m 35s {color} | {color:green} trunk passed {color} |\n| {color:green}+1{color} | {color:green} compile {color} | {color:green} 0m 22s {color} | {color:green} trunk passed {color} |\n| {color:green}+1{color} | {color:green} checkstyle {color} | {color:green} 0m 15s {color} | {color:green} trunk passed {color} |\n| {color:green}+1{color} | {color:green} mvnsite {color} | {color:green} 0m 27s {color} | {color:green} trunk passed {color} |\n| {color:green}+1{color} | {color:green} mvneclipse {color} | {color:green} 0m 18s {color} | {color:green} trunk passed {color} |\n| {color:green}+1{color} | {color:green} findbugs {color} | {color:green} 0m 34s {color} | {color:green} trunk passed {color} |\n| {color:green}+1{color} | {color:green} javadoc {color} | {color:green} 0m 13s {color} | {color:green} trunk passed {color} |\n| {color:green}+1{color} | {color:green} mvninstall {color} | {color:green} 0m 21s {color} | {color:green} the patch passed {color} |\n| {color:green}+1{color} | {color:green} compile {color} | {color:green} 0m 21s {color} | {color:green} the patch passed {color} |\n| {color:green}+1{color} | {color:green} javac {color} | {color:green} 0m 21s {color} | {color:green} the patch passed {color} |\n| {color:green}+1{color} | {color:green} checkstyle {color} | {color:green} 0m 12s {color} | {color:green} the patch passed {color} |\n| {color:green}+1{color} | {color:green} mvnsite {color} | {color:green} 0m 23s {color} | {color:green} the patch passed {color} |\n| {color:green}+1{color} | {color:green} mvneclipse {color} | {color:green} 0m 14s {color} | {color:green} the patch passed {color} |\n| {color:green}+1{color} | {color:green} whitespace {color} | {color:green} 0m 0s {color} | {color:green} The patch has no whitespace issues. {color} |\n| {color:green}+1{color} | {color:green} findbugs {color} | {color:green} 0m 39s {color} | {color:green} the patch passed {color} |\n| {color:green}+1{color} | {color:green} javadoc {color} | {color:green} 0m 10s {color} | {color:green} the patch passed {color} |\n| {color:green}+1{color} | {color:green} unit {color} | {color:green} 9m 7s {color} | {color:green} hadoop-mapreduce-client-app in the patch passed. {color} |\n| {color:green}+1{color} | {color:green} asflicense {color} | {color:green} 0m 18s {color} | {color:green} The patch does not generate ASF License warnings. {color} |\n| {color:black}{color} | {color:black} {color} | {color:black} 27m 19s {color} | {color:black} {color} |\n\\\\\n\\\\\n|| Subsystem || Report/Notes ||\n| Docker |  Image:yetus/hadoop:14b5c93 |\n| JIRA Patch URL | https://issues.apache.org/jira/secure/attachment/12810463/MAPREDUCE-6697-v1.patch |\n| JIRA Issue | MAPREDUCE-6697 |\n| Optional Tests |  asflicense  compile  javac  javadoc  mvninstall  mvnsite  unit  findbugs  checkstyle  |\n| uname | Linux 20048d93b059 4.4.0-43-generic #63-Ubuntu SMP Wed Oct 12 13:48:03 UTC 2016 x86_64 x86_64 x86_64 GNU/Linux |\n| Build tool | maven |\n| Personality | /testptch/hadoop/patchprocess/precommit/personality/provided.sh |\n| git revision | trunk / e86eef9 |\n| Default Java | 1.8.0_131 |\n| findbugs | v3.1.0-RC1 |\n|  Test Results | https://builds.apache.org/job/PreCommit-MAPREDUCE-Build/6992/testReport/ |\n| modules | C: hadoop-mapreduce-project/hadoop-mapreduce-client/hadoop-mapreduce-client-app U: hadoop-mapreduce-project/hadoop-mapreduce-client/hadoop-mapreduce-client-app |\n| Console output | https://builds.apache.org/job/PreCommit-MAPREDUCE-Build/6992/console |\n| Powered by | Apache Yetus 0.3.0   http://yetus.apache.org |\n\n\nThis message was automatically generated.\n\n", "updateAuthor": {"self": "https://issues.apache.org/jira/rest/api/2/user?username=hadoopqa", "name": "hadoopqa", "key": "hadoopqa", "avatarUrls": {"48x48": "https://issues.apache.org/jira/secure/useravatar?ownerId=hadoopqa&avatarId=10393", "24x24": "https://issues.apache.org/jira/secure/useravatar?size=small&ownerId=hadoopqa&avatarId=10393", "16x16": "https://issues.apache.org/jira/secure/useravatar?size=xsmall&ownerId=hadoopqa&avatarId=10393", "32x32": "https://issues.apache.org/jira/secure/useravatar?size=medium&ownerId=hadoopqa&avatarId=10393"}, "displayName": "Hadoop QA", "active": true, "timeZone": "Etc/UTC"}, "created": "2017-06-12T10:05:53.702+0000", "updated": "2017-06-12T10:05:53.702+0000"}, {"self": "https://issues.apache.org/jira/rest/api/2/issue/12970130/comment/16065538", "id": "16065538", "author": {"self": "https://issues.apache.org/jira/rest/api/2/user?username=nroberts", "name": "nroberts", "key": "nroberts", "avatarUrls": {"48x48": "https://issues.apache.org/jira/secure/useravatar?avatarId=10452", "24x24": "https://issues.apache.org/jira/secure/useravatar?size=small&avatarId=10452", "16x16": "https://issues.apache.org/jira/secure/useravatar?size=xsmall&avatarId=10452", "32x32": "https://issues.apache.org/jira/secure/useravatar?size=medium&avatarId=10452"}, "displayName": "Nathan Roberts", "active": true, "timeZone": "America/Chicago"}, "body": "@aajisaka Thanks for taking a look. I don't believe there was a specific reason for the 3 invocations. I think it was just to make sure a few heartbeats were simulated. ", "updateAuthor": {"self": "https://issues.apache.org/jira/rest/api/2/user?username=nroberts", "name": "nroberts", "key": "nroberts", "avatarUrls": {"48x48": "https://issues.apache.org/jira/secure/useravatar?avatarId=10452", "24x24": "https://issues.apache.org/jira/secure/useravatar?size=small&avatarId=10452", "16x16": "https://issues.apache.org/jira/secure/useravatar?size=xsmall&avatarId=10452", "32x32": "https://issues.apache.org/jira/secure/useravatar?size=medium&avatarId=10452"}, "displayName": "Nathan Roberts", "active": true, "timeZone": "America/Chicago"}, "created": "2017-06-27T21:49:30.910+0000", "updated": "2017-06-27T21:49:30.910+0000"}, {"self": "https://issues.apache.org/jira/rest/api/2/issue/12970130/comment/16065796", "id": "16065796", "author": {"self": "https://issues.apache.org/jira/rest/api/2/user?username=aajisaka", "name": "aajisaka", "key": "ajisakaa", "avatarUrls": {"48x48": "https://issues.apache.org/jira/secure/useravatar?ownerId=ajisakaa&avatarId=17238", "24x24": "https://issues.apache.org/jira/secure/useravatar?size=small&ownerId=ajisakaa&avatarId=17238", "16x16": "https://issues.apache.org/jira/secure/useravatar?size=xsmall&ownerId=ajisakaa&avatarId=17238", "32x32": "https://issues.apache.org/jira/secure/useravatar?size=medium&ownerId=ajisakaa&avatarId=17238"}, "displayName": "Akira Ajisaka", "active": true, "timeZone": "Asia/Tokyo"}, "body": "Thank you, Nathan. It makes sense. I'm +1 for the patch.", "updateAuthor": {"self": "https://issues.apache.org/jira/rest/api/2/user?username=aajisaka", "name": "aajisaka", "key": "ajisakaa", "avatarUrls": {"48x48": "https://issues.apache.org/jira/secure/useravatar?ownerId=ajisakaa&avatarId=17238", "24x24": "https://issues.apache.org/jira/secure/useravatar?size=small&ownerId=ajisakaa&avatarId=17238", "16x16": "https://issues.apache.org/jira/secure/useravatar?size=xsmall&ownerId=ajisakaa&avatarId=17238", "32x32": "https://issues.apache.org/jira/secure/useravatar?size=medium&ownerId=ajisakaa&avatarId=17238"}, "displayName": "Akira Ajisaka", "active": true, "timeZone": "Asia/Tokyo"}, "created": "2017-06-28T01:47:20.425+0000", "updated": "2017-06-28T01:47:20.425+0000"}, {"self": "https://issues.apache.org/jira/rest/api/2/issue/12970130/comment/16065819", "id": "16065819", "author": {"self": "https://issues.apache.org/jira/rest/api/2/user?username=hudson", "name": "hudson", "key": "hudson", "avatarUrls": {"48x48": "https://issues.apache.org/jira/secure/useravatar?avatarId=10452", "24x24": "https://issues.apache.org/jira/secure/useravatar?size=small&avatarId=10452", "16x16": "https://issues.apache.org/jira/secure/useravatar?size=xsmall&avatarId=10452", "32x32": "https://issues.apache.org/jira/secure/useravatar?size=medium&avatarId=10452"}, "displayName": "Hudson", "active": true, "timeZone": "Etc/UTC"}, "body": "SUCCESS: Integrated in Jenkins build Hadoop-trunk-Commit #11938 (See [https://builds.apache.org/job/Hadoop-trunk-Commit/11938/])\nMAPREDUCE-6697. Concurrent task limits should only be applied when (aajisaka: rev a5c0476a990ec1e7eb34ce2462a45aa52cc1350d)\n* (edit) hadoop-mapreduce-project/hadoop-mapreduce-client/hadoop-mapreduce-client-app/src/main/java/org/apache/hadoop/mapreduce/v2/app/rm/RMContainerAllocator.java\n* (edit) hadoop-mapreduce-project/hadoop-mapreduce-client/hadoop-mapreduce-client-app/src/test/java/org/apache/hadoop/mapreduce/v2/app/rm/TestRMContainerAllocator.java\n", "updateAuthor": {"self": "https://issues.apache.org/jira/rest/api/2/user?username=hudson", "name": "hudson", "key": "hudson", "avatarUrls": {"48x48": "https://issues.apache.org/jira/secure/useravatar?avatarId=10452", "24x24": "https://issues.apache.org/jira/secure/useravatar?size=small&avatarId=10452", "16x16": "https://issues.apache.org/jira/secure/useravatar?size=xsmall&avatarId=10452", "32x32": "https://issues.apache.org/jira/secure/useravatar?size=medium&avatarId=10452"}, "displayName": "Hudson", "active": true, "timeZone": "Etc/UTC"}, "created": "2017-06-28T02:14:07.313+0000", "updated": "2017-06-28T02:14:07.313+0000"}, {"self": "https://issues.apache.org/jira/rest/api/2/issue/12970130/comment/16065853", "id": "16065853", "author": {"self": "https://issues.apache.org/jira/rest/api/2/user?username=aajisaka", "name": "aajisaka", "key": "ajisakaa", "avatarUrls": {"48x48": "https://issues.apache.org/jira/secure/useravatar?ownerId=ajisakaa&avatarId=17238", "24x24": "https://issues.apache.org/jira/secure/useravatar?size=small&ownerId=ajisakaa&avatarId=17238", "16x16": "https://issues.apache.org/jira/secure/useravatar?size=xsmall&ownerId=ajisakaa&avatarId=17238", "32x32": "https://issues.apache.org/jira/secure/useravatar?size=medium&ownerId=ajisakaa&avatarId=17238"}, "displayName": "Akira Ajisaka", "active": true, "timeZone": "Asia/Tokyo"}, "body": "Committed this to trunk and branch-2. Hi [~nroberts], would you create a patch for branch-2.8? This patch applies to branch-2.8 but compilation error occurs.\n{noformat}\n[INFO] -------------------------------------------------------------\n[ERROR] COMPILATION ERROR : \n[INFO] -------------------------------------------------------------\n[ERROR] /Users/ajisaka/git/hadoop/hadoop-mapreduce-project/hadoop-mapreduce-client/hadoop-mapreduce-client-app/src/test/java/org/apache/hadoop/mapreduce/v2/app/rm/TestRMContainerAllocator.java:[2759,24] cannot find symbol\n  symbol:   method getInstance()\n  location: class org.apache.hadoop.yarn.util.SystemClock\n[INFO] 1 error\n{noformat}", "updateAuthor": {"self": "https://issues.apache.org/jira/rest/api/2/user?username=aajisaka", "name": "aajisaka", "key": "ajisakaa", "avatarUrls": {"48x48": "https://issues.apache.org/jira/secure/useravatar?ownerId=ajisakaa&avatarId=17238", "24x24": "https://issues.apache.org/jira/secure/useravatar?size=small&ownerId=ajisakaa&avatarId=17238", "16x16": "https://issues.apache.org/jira/secure/useravatar?size=xsmall&ownerId=ajisakaa&avatarId=17238", "32x32": "https://issues.apache.org/jira/secure/useravatar?size=medium&ownerId=ajisakaa&avatarId=17238"}, "displayName": "Akira Ajisaka", "active": true, "timeZone": "Asia/Tokyo"}, "created": "2017-06-28T02:52:23.291+0000", "updated": "2017-06-28T02:52:23.291+0000"}, {"self": "https://issues.apache.org/jira/rest/api/2/issue/12970130/comment/16069261", "id": "16069261", "author": {"self": "https://issues.apache.org/jira/rest/api/2/user?username=andrew.wang", "name": "andrew.wang", "key": "andrew.wang", "avatarUrls": {"48x48": "https://issues.apache.org/jira/secure/useravatar?ownerId=andrew.wang&avatarId=19230", "24x24": "https://issues.apache.org/jira/secure/useravatar?size=small&ownerId=andrew.wang&avatarId=19230", "16x16": "https://issues.apache.org/jira/secure/useravatar?size=xsmall&ownerId=andrew.wang&avatarId=19230", "32x32": "https://issues.apache.org/jira/secure/useravatar?size=medium&ownerId=andrew.wang&avatarId=19230"}, "displayName": "Andrew Wang", "active": true, "timeZone": "America/Los_Angeles"}, "body": "I'm going to close this so I can roll a release, please re-open if you need a Jenkins run after.", "updateAuthor": {"self": "https://issues.apache.org/jira/rest/api/2/user?username=andrew.wang", "name": "andrew.wang", "key": "andrew.wang", "avatarUrls": {"48x48": "https://issues.apache.org/jira/secure/useravatar?ownerId=andrew.wang&avatarId=19230", "24x24": "https://issues.apache.org/jira/secure/useravatar?size=small&ownerId=andrew.wang&avatarId=19230", "16x16": "https://issues.apache.org/jira/secure/useravatar?size=xsmall&ownerId=andrew.wang&avatarId=19230", "32x32": "https://issues.apache.org/jira/secure/useravatar?size=medium&ownerId=andrew.wang&avatarId=19230"}, "displayName": "Andrew Wang", "active": true, "timeZone": "America/Los_Angeles"}, "created": "2017-06-30T00:26:19.346+0000", "updated": "2017-06-30T00:26:19.346+0000"}, {"self": "https://issues.apache.org/jira/rest/api/2/issue/12970130/comment/16083308", "id": "16083308", "author": {"self": "https://issues.apache.org/jira/rest/api/2/user?username=zhouyejoe", "name": "zhouyejoe", "key": "zhouyejoe", "avatarUrls": {"48x48": "https://issues.apache.org/jira/secure/useravatar?avatarId=10452", "24x24": "https://issues.apache.org/jira/secure/useravatar?size=small&avatarId=10452", "16x16": "https://issues.apache.org/jira/secure/useravatar?size=xsmall&avatarId=10452", "32x32": "https://issues.apache.org/jira/secure/useravatar?size=medium&avatarId=10452"}, "displayName": "Ye Zhou", "active": true, "timeZone": "America/Los_Angeles"}, "body": "Hi, [~nroberts]. Would you also create a patch for 2.7 branch? This should be helpful for the ongoing 2.7.4 release. Thanks.", "updateAuthor": {"self": "https://issues.apache.org/jira/rest/api/2/user?username=zhouyejoe", "name": "zhouyejoe", "key": "zhouyejoe", "avatarUrls": {"48x48": "https://issues.apache.org/jira/secure/useravatar?avatarId=10452", "24x24": "https://issues.apache.org/jira/secure/useravatar?size=small&avatarId=10452", "16x16": "https://issues.apache.org/jira/secure/useravatar?size=xsmall&avatarId=10452", "32x32": "https://issues.apache.org/jira/secure/useravatar?size=medium&avatarId=10452"}, "displayName": "Ye Zhou", "active": true, "timeZone": "America/Los_Angeles"}, "created": "2017-07-12T01:59:32.963+0000", "updated": "2017-07-12T01:59:32.963+0000"}, {"self": "https://issues.apache.org/jira/rest/api/2/issue/12970130/comment/16084100", "id": "16084100", "author": {"self": "https://issues.apache.org/jira/rest/api/2/user?username=nroberts", "name": "nroberts", "key": "nroberts", "avatarUrls": {"48x48": "https://issues.apache.org/jira/secure/useravatar?avatarId=10452", "24x24": "https://issues.apache.org/jira/secure/useravatar?size=small&avatarId=10452", "16x16": "https://issues.apache.org/jira/secure/useravatar?size=xsmall&avatarId=10452", "32x32": "https://issues.apache.org/jira/secure/useravatar?size=medium&avatarId=10452"}, "displayName": "Nathan Roberts", "active": true, "timeZone": "America/Chicago"}, "body": "Adding patch for 2.8/2.7", "updateAuthor": {"self": "https://issues.apache.org/jira/rest/api/2/user?username=nroberts", "name": "nroberts", "key": "nroberts", "avatarUrls": {"48x48": "https://issues.apache.org/jira/secure/useravatar?avatarId=10452", "24x24": "https://issues.apache.org/jira/secure/useravatar?size=small&avatarId=10452", "16x16": "https://issues.apache.org/jira/secure/useravatar?size=xsmall&avatarId=10452", "32x32": "https://issues.apache.org/jira/secure/useravatar?size=medium&avatarId=10452"}, "displayName": "Nathan Roberts", "active": true, "timeZone": "America/Chicago"}, "created": "2017-07-12T14:59:40.970+0000", "updated": "2017-07-12T14:59:40.970+0000"}, {"self": "https://issues.apache.org/jira/rest/api/2/issue/12970130/comment/16084101", "id": "16084101", "author": {"self": "https://issues.apache.org/jira/rest/api/2/user?username=nroberts", "name": "nroberts", "key": "nroberts", "avatarUrls": {"48x48": "https://issues.apache.org/jira/secure/useravatar?avatarId=10452", "24x24": "https://issues.apache.org/jira/secure/useravatar?size=small&avatarId=10452", "16x16": "https://issues.apache.org/jira/secure/useravatar?size=xsmall&avatarId=10452", "32x32": "https://issues.apache.org/jira/secure/useravatar?size=medium&avatarId=10452"}, "displayName": "Nathan Roberts", "active": true, "timeZone": "America/Chicago"}, "body": "Applies to branch-2.8 and branch-2.7", "updateAuthor": {"self": "https://issues.apache.org/jira/rest/api/2/user?username=nroberts", "name": "nroberts", "key": "nroberts", "avatarUrls": {"48x48": "https://issues.apache.org/jira/secure/useravatar?avatarId=10452", "24x24": "https://issues.apache.org/jira/secure/useravatar?size=small&avatarId=10452", "16x16": "https://issues.apache.org/jira/secure/useravatar?size=xsmall&avatarId=10452", "32x32": "https://issues.apache.org/jira/secure/useravatar?size=medium&avatarId=10452"}, "displayName": "Nathan Roberts", "active": true, "timeZone": "America/Chicago"}, "created": "2017-07-12T15:00:31.897+0000", "updated": "2017-07-12T15:00:31.897+0000"}, {"self": "https://issues.apache.org/jira/rest/api/2/issue/12970130/comment/16084189", "id": "16084189", "author": {"self": "https://issues.apache.org/jira/rest/api/2/user?username=hadoopqa", "name": "hadoopqa", "key": "hadoopqa", "avatarUrls": {"48x48": "https://issues.apache.org/jira/secure/useravatar?ownerId=hadoopqa&avatarId=10393", "24x24": "https://issues.apache.org/jira/secure/useravatar?size=small&ownerId=hadoopqa&avatarId=10393", "16x16": "https://issues.apache.org/jira/secure/useravatar?size=xsmall&ownerId=hadoopqa&avatarId=10393", "32x32": "https://issues.apache.org/jira/secure/useravatar?size=medium&ownerId=hadoopqa&avatarId=10393"}, "displayName": "Hadoop QA", "active": true, "timeZone": "Etc/UTC"}, "body": "| (/) *{color:green}+1 overall{color}* |\n\\\\\n\\\\\n|| Vote || Subsystem || Runtime || Comment ||\n| {color:blue}0{color} | {color:blue} reexec {color} | {color:blue}  0m 20s{color} | {color:blue} Docker mode activated. {color} |\n| {color:green}+1{color} | {color:green} @author {color} | {color:green}  0m  0s{color} | {color:green} The patch does not contain any @author tags. {color} |\n| {color:green}+1{color} | {color:green} test4tests {color} | {color:green}  0m  0s{color} | {color:green} The patch appears to include 1 new or modified test files. {color} |\n| {color:green}+1{color} | {color:green} mvninstall {color} | {color:green}  9m  6s{color} | {color:green} branch-2.8 passed {color} |\n| {color:green}+1{color} | {color:green} compile {color} | {color:green}  0m 20s{color} | {color:green} branch-2.8 passed with JDK v1.8.0_131 {color} |\n| {color:green}+1{color} | {color:green} compile {color} | {color:green}  0m 26s{color} | {color:green} branch-2.8 passed with JDK v1.7.0_131 {color} |\n| {color:green}+1{color} | {color:green} checkstyle {color} | {color:green}  0m 18s{color} | {color:green} branch-2.8 passed {color} |\n| {color:green}+1{color} | {color:green} mvnsite {color} | {color:green}  0m 30s{color} | {color:green} branch-2.8 passed {color} |\n| {color:green}+1{color} | {color:green} mvneclipse {color} | {color:green}  0m 18s{color} | {color:green} branch-2.8 passed {color} |\n| {color:green}+1{color} | {color:green} findbugs {color} | {color:green}  0m 48s{color} | {color:green} branch-2.8 passed {color} |\n| {color:green}+1{color} | {color:green} javadoc {color} | {color:green}  0m 16s{color} | {color:green} branch-2.8 passed with JDK v1.8.0_131 {color} |\n| {color:green}+1{color} | {color:green} javadoc {color} | {color:green}  0m 18s{color} | {color:green} branch-2.8 passed with JDK v1.7.0_131 {color} |\n| {color:green}+1{color} | {color:green} mvninstall {color} | {color:green}  0m 24s{color} | {color:green} the patch passed {color} |\n| {color:green}+1{color} | {color:green} compile {color} | {color:green}  0m 19s{color} | {color:green} the patch passed with JDK v1.8.0_131 {color} |\n| {color:green}+1{color} | {color:green} javac {color} | {color:green}  0m 19s{color} | {color:green} the patch passed {color} |\n| {color:green}+1{color} | {color:green} compile {color} | {color:green}  0m 22s{color} | {color:green} the patch passed with JDK v1.7.0_131 {color} |\n| {color:green}+1{color} | {color:green} javac {color} | {color:green}  0m 22s{color} | {color:green} the patch passed {color} |\n| {color:green}+1{color} | {color:green} checkstyle {color} | {color:green}  0m 15s{color} | {color:green} the patch passed {color} |\n| {color:green}+1{color} | {color:green} mvnsite {color} | {color:green}  0m 26s{color} | {color:green} the patch passed {color} |\n| {color:green}+1{color} | {color:green} mvneclipse {color} | {color:green}  0m 13s{color} | {color:green} the patch passed {color} |\n| {color:green}+1{color} | {color:green} whitespace {color} | {color:green}  0m  0s{color} | {color:green} The patch has no whitespace issues. {color} |\n| {color:green}+1{color} | {color:green} findbugs {color} | {color:green}  0m 57s{color} | {color:green} the patch passed {color} |\n| {color:green}+1{color} | {color:green} javadoc {color} | {color:green}  0m 12s{color} | {color:green} the patch passed with JDK v1.8.0_131 {color} |\n| {color:green}+1{color} | {color:green} javadoc {color} | {color:green}  0m 16s{color} | {color:green} the patch passed with JDK v1.7.0_131 {color} |\n| {color:green}+1{color} | {color:green} unit {color} | {color:green} 10m  2s{color} | {color:green} hadoop-mapreduce-client-app in the patch passed with JDK v1.7.0_131. {color} |\n| {color:green}+1{color} | {color:green} asflicense {color} | {color:green}  0m 17s{color} | {color:green} The patch does not generate ASF License warnings. {color} |\n| {color:black}{color} | {color:black} {color} | {color:black} 36m 43s{color} | {color:black} {color} |\n\\\\\n\\\\\n|| Subsystem || Report/Notes ||\n| Docker |  Image:yetus/hadoop:d946387 |\n| JIRA Issue | MAPREDUCE-6697 |\n| JIRA Patch URL | https://issues.apache.org/jira/secure/attachment/12876863/MAPREDUCE-6697-branch-2.8.001.patch |\n| Optional Tests |  asflicense  compile  javac  javadoc  mvninstall  mvnsite  unit  findbugs  checkstyle  |\n| uname | Linux 09b34b6a11b8 3.13.0-117-generic #164-Ubuntu SMP Fri Apr 7 11:05:26 UTC 2017 x86_64 x86_64 x86_64 GNU/Linux |\n| Build tool | maven |\n| Personality | /testptch/hadoop/patchprocess/precommit/personality/provided.sh |\n| git revision | branch-2.8 / ebb66d2 |\n| Default Java | 1.7.0_131 |\n| Multi-JDK versions |  /usr/lib/jvm/java-8-oracle:1.8.0_131 /usr/lib/jvm/java-7-openjdk-amd64:1.7.0_131 |\n| findbugs | v3.0.0 |\n| JDK v1.7.0_131  Test Results | https://builds.apache.org/job/PreCommit-MAPREDUCE-Build/7025/testReport/ |\n| modules | C: hadoop-mapreduce-project/hadoop-mapreduce-client/hadoop-mapreduce-client-app U: hadoop-mapreduce-project/hadoop-mapreduce-client/hadoop-mapreduce-client-app |\n| Console output | https://builds.apache.org/job/PreCommit-MAPREDUCE-Build/7025/console |\n| Powered by | Apache Yetus 0.4.0   http://yetus.apache.org |\n\n\nThis message was automatically generated.\n\n", "updateAuthor": {"self": "https://issues.apache.org/jira/rest/api/2/user?username=hadoopqa", "name": "hadoopqa", "key": "hadoopqa", "avatarUrls": {"48x48": "https://issues.apache.org/jira/secure/useravatar?ownerId=hadoopqa&avatarId=10393", "24x24": "https://issues.apache.org/jira/secure/useravatar?size=small&ownerId=hadoopqa&avatarId=10393", "16x16": "https://issues.apache.org/jira/secure/useravatar?size=xsmall&ownerId=hadoopqa&avatarId=10393", "32x32": "https://issues.apache.org/jira/secure/useravatar?size=medium&ownerId=hadoopqa&avatarId=10393"}, "displayName": "Hadoop QA", "active": true, "timeZone": "Etc/UTC"}, "created": "2017-07-12T15:45:10.774+0000", "updated": "2017-07-12T15:45:10.774+0000"}, {"self": "https://issues.apache.org/jira/rest/api/2/issue/12970130/comment/16084628", "id": "16084628", "author": {"self": "https://issues.apache.org/jira/rest/api/2/user?username=zhouyejoe", "name": "zhouyejoe", "key": "zhouyejoe", "avatarUrls": {"48x48": "https://issues.apache.org/jira/secure/useravatar?avatarId=10452", "24x24": "https://issues.apache.org/jira/secure/useravatar?size=small&avatarId=10452", "16x16": "https://issues.apache.org/jira/secure/useravatar?size=xsmall&avatarId=10452", "32x32": "https://issues.apache.org/jira/secure/useravatar?size=medium&avatarId=10452"}, "displayName": "Ye Zhou", "active": true, "timeZone": "America/Los_Angeles"}, "body": "[~nroberts]Thanks.\nHi, [~shv]. Please check the 2.7 patch.", "updateAuthor": {"self": "https://issues.apache.org/jira/rest/api/2/user?username=zhouyejoe", "name": "zhouyejoe", "key": "zhouyejoe", "avatarUrls": {"48x48": "https://issues.apache.org/jira/secure/useravatar?avatarId=10452", "24x24": "https://issues.apache.org/jira/secure/useravatar?size=small&avatarId=10452", "16x16": "https://issues.apache.org/jira/secure/useravatar?size=xsmall&avatarId=10452", "32x32": "https://issues.apache.org/jira/secure/useravatar?size=medium&avatarId=10452"}, "displayName": "Ye Zhou", "active": true, "timeZone": "America/Los_Angeles"}, "created": "2017-07-12T20:25:32.669+0000", "updated": "2017-07-12T20:25:32.669+0000"}, {"self": "https://issues.apache.org/jira/rest/api/2/issue/12970130/comment/16084851", "id": "16084851", "author": {"self": "https://issues.apache.org/jira/rest/api/2/user?username=shv", "name": "shv", "key": "shv", "avatarUrls": {"48x48": "https://issues.apache.org/jira/secure/useravatar?avatarId=10452", "24x24": "https://issues.apache.org/jira/secure/useravatar?size=small&avatarId=10452", "16x16": "https://issues.apache.org/jira/secure/useravatar?size=xsmall&avatarId=10452", "32x32": "https://issues.apache.org/jira/secure/useravatar?size=medium&avatarId=10452"}, "displayName": "Konstantin Shvachko", "active": true, "timeZone": "America/Los_Angeles"}, "body": "The patch applies cleanly to 2.7, and TestRMContainerAllocator passes.\nLet's just reattach the same patch for a full Jenkins run on branch-2.7.", "updateAuthor": {"self": "https://issues.apache.org/jira/rest/api/2/user?username=shv", "name": "shv", "key": "shv", "avatarUrls": {"48x48": "https://issues.apache.org/jira/secure/useravatar?avatarId=10452", "24x24": "https://issues.apache.org/jira/secure/useravatar?size=small&avatarId=10452", "16x16": "https://issues.apache.org/jira/secure/useravatar?size=xsmall&avatarId=10452", "32x32": "https://issues.apache.org/jira/secure/useravatar?size=medium&avatarId=10452"}, "displayName": "Konstantin Shvachko", "active": true, "timeZone": "America/Los_Angeles"}, "created": "2017-07-12T22:39:52.503+0000", "updated": "2017-07-12T22:39:52.503+0000"}, {"self": "https://issues.apache.org/jira/rest/api/2/issue/12970130/comment/16084906", "id": "16084906", "author": {"self": "https://issues.apache.org/jira/rest/api/2/user?username=hadoopqa", "name": "hadoopqa", "key": "hadoopqa", "avatarUrls": {"48x48": "https://issues.apache.org/jira/secure/useravatar?ownerId=hadoopqa&avatarId=10393", "24x24": "https://issues.apache.org/jira/secure/useravatar?size=small&ownerId=hadoopqa&avatarId=10393", "16x16": "https://issues.apache.org/jira/secure/useravatar?size=xsmall&ownerId=hadoopqa&avatarId=10393", "32x32": "https://issues.apache.org/jira/secure/useravatar?size=medium&ownerId=hadoopqa&avatarId=10393"}, "displayName": "Hadoop QA", "active": true, "timeZone": "Etc/UTC"}, "body": "| (x) *{color:red}-1 overall{color}* |\n\\\\\n\\\\\n|| Vote || Subsystem || Runtime || Comment ||\n| {color:blue}0{color} | {color:blue} reexec {color} | {color:blue} 11m 36s{color} | {color:blue} Docker mode activated. {color} |\n| {color:green}+1{color} | {color:green} @author {color} | {color:green}  0m  0s{color} | {color:green} The patch does not contain any @author tags. {color} |\n| {color:green}+1{color} | {color:green} test4tests {color} | {color:green}  0m  0s{color} | {color:green} The patch appears to include 1 new or modified test files. {color} |\n| {color:green}+1{color} | {color:green} mvninstall {color} | {color:green}  5m 53s{color} | {color:green} branch-2.7 passed {color} |\n| {color:green}+1{color} | {color:green} compile {color} | {color:green}  0m 18s{color} | {color:green} branch-2.7 passed with JDK v1.8.0_131 {color} |\n| {color:green}+1{color} | {color:green} compile {color} | {color:green}  0m 22s{color} | {color:green} branch-2.7 passed with JDK v1.7.0_131 {color} |\n| {color:green}+1{color} | {color:green} checkstyle {color} | {color:green}  0m 22s{color} | {color:green} branch-2.7 passed {color} |\n| {color:green}+1{color} | {color:green} mvnsite {color} | {color:green}  0m 27s{color} | {color:green} branch-2.7 passed {color} |\n| {color:green}+1{color} | {color:green} mvneclipse {color} | {color:green}  0m 14s{color} | {color:green} branch-2.7 passed {color} |\n| {color:red}-1{color} | {color:red} findbugs {color} | {color:red}  0m 42s{color} | {color:red} hadoop-mapreduce-project/hadoop-mapreduce-client/hadoop-mapreduce-client-app in branch-2.7 has 1 extant Findbugs warnings. {color} |\n| {color:green}+1{color} | {color:green} javadoc {color} | {color:green}  0m 13s{color} | {color:green} branch-2.7 passed with JDK v1.8.0_131 {color} |\n| {color:green}+1{color} | {color:green} javadoc {color} | {color:green}  0m 17s{color} | {color:green} branch-2.7 passed with JDK v1.7.0_131 {color} |\n| {color:green}+1{color} | {color:green} mvninstall {color} | {color:green}  0m 20s{color} | {color:green} the patch passed {color} |\n| {color:green}+1{color} | {color:green} compile {color} | {color:green}  0m 16s{color} | {color:green} the patch passed with JDK v1.8.0_131 {color} |\n| {color:green}+1{color} | {color:green} javac {color} | {color:green}  0m 16s{color} | {color:green} the patch passed {color} |\n| {color:green}+1{color} | {color:green} compile {color} | {color:green}  0m 20s{color} | {color:green} the patch passed with JDK v1.7.0_131 {color} |\n| {color:green}+1{color} | {color:green} javac {color} | {color:green}  0m 20s{color} | {color:green} the patch passed {color} |\n| {color:red}-1{color} | {color:red} checkstyle {color} | {color:red}  0m 18s{color} | {color:red} hadoop-mapreduce-project/hadoop-mapreduce-client/hadoop-mapreduce-client-app: The patch generated 2 new + 390 unchanged - 0 fixed = 392 total (was 390) {color} |\n| {color:green}+1{color} | {color:green} mvnsite {color} | {color:green}  0m 24s{color} | {color:green} the patch passed {color} |\n| {color:green}+1{color} | {color:green} mvneclipse {color} | {color:green}  0m 12s{color} | {color:green} the patch passed {color} |\n| {color:red}-1{color} | {color:red} whitespace {color} | {color:red}  0m  0s{color} | {color:red} The patch has 2226 line(s) that end in whitespace. Use git apply --whitespace=fix <<patch_file>>. Refer https://git-scm.com/docs/git-apply {color} |\n| {color:red}-1{color} | {color:red} whitespace {color} | {color:red}  1m  1s{color} | {color:red} The patch 74 line(s) with tabs. {color} |\n| {color:green}+1{color} | {color:green} findbugs {color} | {color:green}  0m 49s{color} | {color:green} the patch passed {color} |\n| {color:green}+1{color} | {color:green} javadoc {color} | {color:green}  0m 10s{color} | {color:green} the patch passed with JDK v1.8.0_131 {color} |\n| {color:green}+1{color} | {color:green} javadoc {color} | {color:green}  0m 13s{color} | {color:green} the patch passed with JDK v1.7.0_131 {color} |\n| {color:green}+1{color} | {color:green} unit {color} | {color:green}  8m 53s{color} | {color:green} hadoop-mapreduce-client-app in the patch passed with JDK v1.7.0_131. {color} |\n| {color:red}-1{color} | {color:red} asflicense {color} | {color:red}  0m 18s{color} | {color:red} The patch generated 7 ASF License warnings. {color} |\n| {color:black}{color} | {color:black} {color} | {color:black} 43m 12s{color} | {color:black} {color} |\n\\\\\n\\\\\n|| Subsystem || Report/Notes ||\n| Docker |  Image:yetus/hadoop:67e87c9 |\n| JIRA Issue | MAPREDUCE-6697 |\n| JIRA Patch URL | https://issues.apache.org/jira/secure/attachment/12876967/MAPREDUCE-6697-branch-2.7.001.patch |\n| Optional Tests |  asflicense  compile  javac  javadoc  mvninstall  mvnsite  unit  findbugs  checkstyle  |\n| uname | Linux 0481734439dc 4.4.0-43-generic #63-Ubuntu SMP Wed Oct 12 13:48:03 UTC 2016 x86_64 x86_64 x86_64 GNU/Linux |\n| Build tool | maven |\n| Personality | /testptch/hadoop/patchprocess/precommit/personality/provided.sh |\n| git revision | branch-2.7 / 187bb77 |\n| Default Java | 1.7.0_131 |\n| Multi-JDK versions |  /usr/lib/jvm/java-8-oracle:1.8.0_131 /usr/lib/jvm/java-7-openjdk-amd64:1.7.0_131 |\n| findbugs | v3.0.0 |\n| findbugs | https://builds.apache.org/job/PreCommit-MAPREDUCE-Build/7026/artifact/patchprocess/branch-findbugs-hadoop-mapreduce-project_hadoop-mapreduce-client_hadoop-mapreduce-client-app-warnings.html |\n| checkstyle | https://builds.apache.org/job/PreCommit-MAPREDUCE-Build/7026/artifact/patchprocess/diff-checkstyle-hadoop-mapreduce-project_hadoop-mapreduce-client_hadoop-mapreduce-client-app.txt |\n| whitespace | https://builds.apache.org/job/PreCommit-MAPREDUCE-Build/7026/artifact/patchprocess/whitespace-eol.txt |\n| whitespace | https://builds.apache.org/job/PreCommit-MAPREDUCE-Build/7026/artifact/patchprocess/whitespace-tabs.txt |\n| JDK v1.7.0_131  Test Results | https://builds.apache.org/job/PreCommit-MAPREDUCE-Build/7026/testReport/ |\n| asflicense | https://builds.apache.org/job/PreCommit-MAPREDUCE-Build/7026/artifact/patchprocess/patch-asflicense-problems.txt |\n| modules | C: hadoop-mapreduce-project/hadoop-mapreduce-client/hadoop-mapreduce-client-app U: hadoop-mapreduce-project/hadoop-mapreduce-client/hadoop-mapreduce-client-app |\n| Console output | https://builds.apache.org/job/PreCommit-MAPREDUCE-Build/7026/console |\n| Powered by | Apache Yetus 0.4.0   http://yetus.apache.org |\n\n\nThis message was automatically generated.\n\n", "updateAuthor": {"self": "https://issues.apache.org/jira/rest/api/2/user?username=hadoopqa", "name": "hadoopqa", "key": "hadoopqa", "avatarUrls": {"48x48": "https://issues.apache.org/jira/secure/useravatar?ownerId=hadoopqa&avatarId=10393", "24x24": "https://issues.apache.org/jira/secure/useravatar?size=small&ownerId=hadoopqa&avatarId=10393", "16x16": "https://issues.apache.org/jira/secure/useravatar?size=xsmall&ownerId=hadoopqa&avatarId=10393", "32x32": "https://issues.apache.org/jira/secure/useravatar?size=medium&ownerId=hadoopqa&avatarId=10393"}, "displayName": "Hadoop QA", "active": true, "timeZone": "Etc/UTC"}, "created": "2017-07-12T23:31:35.446+0000", "updated": "2017-07-12T23:31:35.446+0000"}, {"self": "https://issues.apache.org/jira/rest/api/2/issue/12970130/comment/16084913", "id": "16084913", "author": {"self": "https://issues.apache.org/jira/rest/api/2/user?username=shv", "name": "shv", "key": "shv", "avatarUrls": {"48x48": "https://issues.apache.org/jira/secure/useravatar?avatarId=10452", "24x24": "https://issues.apache.org/jira/secure/useravatar?size=small&avatarId=10452", "16x16": "https://issues.apache.org/jira/secure/useravatar?size=xsmall&avatarId=10452", "32x32": "https://issues.apache.org/jira/secure/useravatar?size=medium&avatarId=10452"}, "displayName": "Konstantin Shvachko", "active": true, "timeZone": "America/Los_Angeles"}, "body": "+1. The patch looks good for both branches.", "updateAuthor": {"self": "https://issues.apache.org/jira/rest/api/2/user?username=shv", "name": "shv", "key": "shv", "avatarUrls": {"48x48": "https://issues.apache.org/jira/secure/useravatar?avatarId=10452", "24x24": "https://issues.apache.org/jira/secure/useravatar?size=small&avatarId=10452", "16x16": "https://issues.apache.org/jira/secure/useravatar?size=xsmall&avatarId=10452", "32x32": "https://issues.apache.org/jira/secure/useravatar?size=medium&avatarId=10452"}, "displayName": "Konstantin Shvachko", "active": true, "timeZone": "America/Los_Angeles"}, "created": "2017-07-12T23:42:58.417+0000", "updated": "2017-07-12T23:42:58.417+0000"}, {"self": "https://issues.apache.org/jira/rest/api/2/issue/12970130/comment/16086447", "id": "16086447", "author": {"self": "https://issues.apache.org/jira/rest/api/2/user?username=shv", "name": "shv", "key": "shv", "avatarUrls": {"48x48": "https://issues.apache.org/jira/secure/useravatar?avatarId=10452", "24x24": "https://issues.apache.org/jira/secure/useravatar?size=small&avatarId=10452", "16x16": "https://issues.apache.org/jira/secure/useravatar?size=xsmall&avatarId=10452", "32x32": "https://issues.apache.org/jira/secure/useravatar?size=medium&avatarId=10452"}, "displayName": "Konstantin Shvachko", "active": true, "timeZone": "America/Los_Angeles"}, "body": "I just committed this to branch 2.8 and branch-2.7. Thank you [~nroberts].", "updateAuthor": {"self": "https://issues.apache.org/jira/rest/api/2/user?username=shv", "name": "shv", "key": "shv", "avatarUrls": {"48x48": "https://issues.apache.org/jira/secure/useravatar?avatarId=10452", "24x24": "https://issues.apache.org/jira/secure/useravatar?size=small&avatarId=10452", "16x16": "https://issues.apache.org/jira/secure/useravatar?size=xsmall&avatarId=10452", "32x32": "https://issues.apache.org/jira/secure/useravatar?size=medium&avatarId=10452"}, "displayName": "Konstantin Shvachko", "active": true, "timeZone": "America/Los_Angeles"}, "created": "2017-07-13T21:40:29.312+0000", "updated": "2017-07-13T21:40:29.312+0000"}], "maxResults": 19, "total": 19, "startAt": 0}, "customfield_12311820": "0|i2y1dj:", "customfield_12314139": null}, "names": {"fixVersions": "Fix Version/s", "resolution": "Resolution", "customfield_12312322": "Git Notification Mailing List", "customfield_12312323": "Github Integration", "customfield_12310420": "Global Rank", "customfield_12312320": "Git Repository Name", "customfield_12312321": "Git Repository Type", "customfield_12312328": "Blog Administrator?", "customfield_12312329": "Blogs - Admin for blog", "customfield_12312326": "Blogs - Username", "customfield_12310300": "Release Version History", "customfield_12312327": "Blogs - Email Address", "customfield_12312324": "Git Repository Import Path", "customfield_12312720": "Docs Text", "customfield_12312325": "New-TLP-TLPName", "lastViewed": "Last Viewed", "priority": "Priority", "labels": "Labels", "customfield_12312333": "Blogs - New Blog Write Access", "customfield_12312334": "Blogs - Existing Blog Name", "customfield_12313422": "Enable Automatic Patch Review", "customfield_12310310": "Attachment count", "customfield_12312331": "Blog - New Blog PMC", "customfield_12312332": "Blog - New Blog Administrators", "aggregatetimeoriginalestimate": "Σ Original Estimate", "timeestimate": "Remaining Estimate", "customfield_12312330": "Blog - Write access", "versions": "Affects Version/s", "customfield_12311120": "Epic Link", "customfield_12313826": "Change Category", "issuelinks": "Linked Issues", "customfield_12312339": "Bugzilla - List of usernames", "customfield_12313825": "Bug Category", "assignee": "Assignee", "customfield_12312337": "Bugzilla - PMC Name", "customfield_12313823": "Test and Documentation Plan", "customfield_12312338": "Bugzilla - Email Notification Address", "customfield_12311920": "issueFunction", "customfield_12313822": "Discovered By", "customfield_12312335": "Blogs - Existing Blog Access Level", "customfield_12313821": "Complexity", "customfield_12312336": "Bugzilla - Project Name", "customfield_12313820": "Severity", "status": "Status", "components": "Component/s", "archiveddate": "Archived", "customfield_12312026": "Initial Confluence Contributors", "customfield_12312023": "Space Name", "customfield_12312024": "Space Description", "aggregatetimeestimate": "Σ Remaining Estimate", "customfield_12312022": "Space Key", "customfield_12310921": "Sprint", "customfield_12310920": "Rank (Obsolete)", "customfield_12312823": "Project", "creator": "Creator", "subtasks": "Sub-Tasks", "reporter": "Reporter", "aggregateprogress": "Σ Progress", "customfield_12313520": "Review Patch?", "customfield_12310250": "Flags", "progress": "Progress", "customfield_12313924": "Source Control Link", "votes": "Votes", "worklog": "Log Work", "archivedby": "Archiver", "customfield_12313920": "Authors", "issuetype": "Issue Type", "timespent": "Time Spent", "customfield_12314020": "Development", "customfield_12314141": "Reviewers", "customfield_12314140": "Ignite Flags", "project": "Project", "aggregatetimespent": "Σ Time Spent", "customfield_12312520": "Github Integrations - Other", "customfield_12312521": "Last public comment date", "customfield_12314422": "Start Date", "customfield_12314421": "Language", "customfield_12314146": "Skill Level", "customfield_12314420": "Mentor", "customfield_12314145": "Affects version (Component)", "customfield_12314144": "Backport to Version", "customfield_12314143": "Fix version (Component)", "resolutiondate": "Resolved", "workratio": "Work Ratio", "customfield_12312923": "Existing GitBox Approval", "customfield_12312920": "Protected Branch", "customfield_12312921": "GitHub Options", "watches": "Watchers", "created": "Created", "customfield_12310192": "Release Note", "customfield_12310191": "Hadoop Flags", "customfield_12310230": "Tags", "updated": "Updated", "timeoriginalestimate": "Original Estimate", "description": "Description", "customfield_10010": "Bugzilla Id", "timetracking": "Time Tracking", "customfield_12314523": "Original story points", "customfield_12314127": "Level of effort", "customfield_12314522": "Target end", "customfield_12314126": "Target Version/s", "customfield_12314521": "Target start", "customfield_12314125": "Bug behavior facts", "customfield_12310320": "Target Version/s", "customfield_12314520": "Parent Link", "customfield_12314124": "Lucene Fields", "customfield_12312340": "Github Integration - Triggers", "attachment": "Attachment", "customfield_12314123": "Workaround", "customfield_12312341": "INFRA - Subversion Repository Path", "customfield_12312220": "Testcase included", "customfield_12314122": "Bugzilla Id", "customfield_12314121": "Estimated Complexity", "customfield_12314120": "Regression", "customfield_12314129": "Review Date", "customfield_12314524": "Team", "customfield_12314128": "Evidence Of Use On World Wide Web", "summary": "Summary", "customfield_12314130": "Evidence Of Registration", "customfield_12310291": "Epic/Theme", "customfield_12310290": "Flagged", "customfield_12311024": "External issue ID", "customfield_12314138": "Reproduced In", "customfield_12314137": "Tags", "environment": "Environment", "customfield_12314136": "Since Version", "customfield_12314135": "Reviewer", "customfield_12311020": "External issue URL", "customfield_12314134": "Hadoop Flags", "duedate": "Due Date", "customfield_12314132": "Issue & fix info", "customfield_12314131": "Evidence Of Open Source Adoption", "comment": "Comment", "customfield_12311820": "Rank", "customfield_12314139": "Tester"}, "schema": {"fixVersions": {"type": "array", "items": "version", "system": "fixVersions"}, "resolution": {"type": "resolution", "system": "resolution"}, "customfield_12312322": {"type": "string", "custom": "com.atlassian.jira.plugin.system.customfieldtypes:textfield", "customId": 12312322}, "customfield_12312323": {"type": "option", "custom": "com.atlassian.jira.plugin.system.customfieldtypes:select", "customId": 12312323}, "customfield_12310420": {"type": "any", "custom": "com.pyxis.greenhopper.jira:gh-global-rank", "customId": 12310420}, "customfield_12312320": {"type": "string", "custom": "com.atlassian.jira.plugin.system.customfieldtypes:textfield", "customId": 12312320}, "customfield_12312321": {"type": "option", "custom": "com.atlassian.jira.plugin.system.customfieldtypes:select", "customId": 12312321}, "customfield_12312328": {"type": "option", "custom": "com.atlassian.jira.plugin.system.customfieldtypes:select", "customId": 12312328}, "customfield_12312329": {"type": "string", "custom": "com.atlassian.jira.plugin.system.customfieldtypes:textfield", "customId": 12312329}, "customfield_12312326": {"type": "string", "custom": "com.atlassian.jira.plugin.system.customfieldtypes:textfield", "customId": 12312326}, "customfield_12310300": {"type": "version", "custom": "com.pyxis.greenhopper.jira:greenhopper-releasedmultiversionhistory", "customId": 12310300}, "customfield_12312327": {"type": "string", "custom": "com.atlassian.jira.plugin.system.customfieldtypes:textfield", "customId": 12312327}, "customfield_12312324": {"type": "string", "custom": "com.atlassian.jira.plugin.system.customfieldtypes:url", "customId": 12312324}, "customfield_12312720": {"type": "string", "custom": "com.atlassian.jira.plugin.system.customfieldtypes:textarea", "customId": 12312720}, "customfield_12312325": {"type": "string", "custom": "com.atlassian.jira.plugin.system.customfieldtypes:textfield", "customId": 12312325}, "lastViewed": {"type": "datetime", "system": "lastViewed"}, "priority": {"type": "priority", "system": "priority"}, "labels": {"type": "array", "items": "string", "system": "labels"}, "customfield_12312333": {"type": "string", "custom": "com.atlassian.jira.plugin.system.customfieldtypes:textarea", "customId": 12312333}, "customfield_12312334": {"type": "string", "custom": "com.atlassian.jira.plugin.system.customfieldtypes:textfield", "customId": 12312334}, "customfield_12313422": {"type": "string", "custom": "com.atlassian.jirafisheyeplugin:jobcheckbox", "customId": 12313422}, "customfield_12310310": {"type": "any", "custom": "com.atlassian.jira.toolkit:attachments", "customId": 12310310}, "customfield_12312331": {"type": "string", "custom": "com.atlassian.jira.plugin.system.customfieldtypes:textfield", "customId": 12312331}, "customfield_12312332": {"type": "string", "custom": "com.atlassian.jira.plugin.system.customfieldtypes:textarea", "customId": 12312332}, "aggregatetimeoriginalestimate": {"type": "number", "system": "aggregatetimeoriginalestimate"}, "timeestimate": {"type": "number", "system": "timeestimate"}, "customfield_12312330": {"type": "string", "custom": "com.atlassian.jira.plugin.system.customfieldtypes:textarea", "customId": 12312330}, "versions": {"type": "array", "items": "version", "system": "versions"}, "customfield_12311120": {"type": "any", "custom": "com.pyxis.greenhopper.jira:gh-epic-link", "customId": 12311120}, "customfield_12313826": {"type": "option", "custom": "com.atlassian.jira.plugin.system.customfieldtypes:select", "customId": 12313826}, "issuelinks": {"type": "array", "items": "issuelinks", "system": "issuelinks"}, "customfield_12312339": {"type": "string", "custom": "com.atlassian.jira.plugin.system.customfieldtypes:textarea", "customId": 12312339}, "customfield_12313825": {"type": "option-with-child", "custom": "com.atlassian.jira.plugin.system.customfieldtypes:cascadingselect", "customId": 12313825}, "assignee": {"type": "user", "system": "assignee"}, "customfield_12312337": {"type": "string", "custom": "com.atlassian.jira.plugin.system.customfieldtypes:textfield", "customId": 12312337}, "customfield_12313823": {"type": "string", "custom": "com.atlassian.jira.plugin.system.customfieldtypes:textarea", "customId": 12313823}, "customfield_12312338": {"type": "string", "custom": "com.atlassian.jira.plugin.system.customfieldtypes:textfield", "customId": 12312338}, "customfield_12311920": {"type": "any", "custom": "com.onresolve.jira.groovy.groovyrunner:jqlFunctionsCustomFieldType", "customId": 12311920}, "customfield_12313822": {"type": "option", "custom": "com.atlassian.jira.plugin.system.customfieldtypes:select", "customId": 12313822}, "customfield_12312335": {"type": "option", "custom": "com.atlassian.jira.plugin.system.customfieldtypes:select", "customId": 12312335}, "customfield_12313821": {"type": "option", "custom": "com.atlassian.jira.plugin.system.customfieldtypes:select", "customId": 12313821}, "customfield_12312336": {"type": "string", "custom": "com.atlassian.jira.plugin.system.customfieldtypes:textfield", "customId": 12312336}, "customfield_12313820": {"type": "option", "custom": "com.atlassian.jira.plugin.system.customfieldtypes:select", "customId": 12313820}, "status": {"type": "status", "system": "status"}, "components": {"type": "array", "items": "component", "system": "components"}, "archiveddate": {"type": "datetime", "system": "archiveddate"}, "customfield_12312026": {"type": "string", "custom": "com.atlassian.jira.plugin.system.customfieldtypes:textfield", "customId": 12312026}, "customfield_12312023": {"type": "string", "custom": "com.atlassian.jira.plugin.system.customfieldtypes:textfield", "customId": 12312023}, "customfield_12312024": {"type": "string", "custom": "com.atlassian.jira.plugin.system.customfieldtypes:textarea", "customId": 12312024}, "aggregatetimeestimate": {"type": "number", "system": "aggregatetimeestimate"}, "customfield_12312022": {"type": "string", "custom": "com.atlassian.jira.plugin.system.customfieldtypes:textfield", "customId": 12312022}, "customfield_12310921": {"type": "array", "items": "string", "custom": "com.pyxis.greenhopper.jira:gh-sprint", "customId": 12310921}, "customfield_12310920": {"type": "any", "custom": "com.pyxis.greenhopper.jira:gh-global-rank", "customId": 12310920}, "customfield_12312823": {"type": "option", "custom": "com.atlassian.jira.plugin.system.customfieldtypes:select", "customId": 12312823}, "creator": {"type": "user", "system": "creator"}, "subtasks": {"type": "array", "items": "issuelinks", "system": "subtasks"}, "reporter": {"type": "user", "system": "reporter"}, "aggregateprogress": {"type": "progress", "system": "aggregateprogress"}, "customfield_12313520": {"type": "array", "items": "option", "custom": "com.atlassian.jira.plugin.system.customfieldtypes:multicheckboxes", "customId": 12313520}, "customfield_12310250": {"type": "array", "items": "option", "custom": "com.atlassian.jira.plugin.system.customfieldtypes:multicheckboxes", "customId": 12310250}, "progress": {"type": "progress", "system": "progress"}, "customfield_12313924": {"type": "string", "custom": "com.atlassian.jira.plugin.system.customfieldtypes:textfield", "customId": 12313924}, "votes": {"type": "votes", "system": "votes"}, "worklog": {"type": "array", "items": "worklog", "system": "worklog"}, "archivedby": {"type": "user", "system": "archivedby"}, "customfield_12313920": {"type": "array", "items": "user", "custom": "com.atlassian.jira.plugin.system.customfieldtypes:multiuserpicker", "customId": 12313920}, "issuetype": {"type": "issuetype", "system": "issuetype"}, "timespent": {"type": "number", "system": "timespent"}, "customfield_12314020": {"type": "any", "custom": "com.atlassian.jira.plugins.jira-development-integration-plugin:devsummary", "customId": 12314020}, "customfield_12314141": {"type": "array", "items": "user", "custom": "com.atlassian.jira.plugin.system.customfieldtypes:multiuserpicker", "customId": 12314141}, "customfield_12314140": {"type": "array", "items": "option", "custom": "com.atlassian.jira.plugin.system.customfieldtypes:multicheckboxes", "customId": 12314140}, "project": {"type": "project", "system": "project"}, "aggregatetimespent": {"type": "number", "system": "aggregatetimespent"}, "customfield_12312520": {"type": "string", "custom": "com.atlassian.jira.plugin.system.customfieldtypes:textfield", "customId": 12312520}, "customfield_12312521": {"type": "any", "custom": "com.atlassian.jira.toolkit:LastCommentDate", "customId": 12312521}, "customfield_12314422": {"type": "date", "custom": "com.atlassian.jira.plugin.system.customfieldtypes:datepicker", "customId": 12314422}, "customfield_12314421": {"type": "array", "items": "string", "custom": "com.atlassian.jira.plugin.system.customfieldtypes:labels", "customId": 12314421}, "customfield_12314146": {"type": "option", "custom": "com.atlassian.jira.plugin.system.customfieldtypes:select", "customId": 12314146}, "customfield_12314420": {"type": "user", "custom": "com.atlassian.jira.plugin.system.customfieldtypes:userpicker", "customId": 12314420}, "customfield_12314145": {"type": "option-with-child", "custom": "com.atlassian.jira.plugin.system.customfieldtypes:cascadingselect", "customId": 12314145}, "customfield_12314144": {"type": "array", "items": "version", "custom": "com.atlassian.jira.plugin.system.customfieldtypes:multiversion", "customId": 12314144}, "customfield_12314143": {"type": "option-with-child", "custom": "com.atlassian.jira.plugin.system.customfieldtypes:cascadingselect", "customId": 12314143}, "resolutiondate": {"type": "datetime", "system": "resolutiondate"}, "workratio": {"type": "number", "system": "workratio"}, "customfield_12312923": {"type": "option", "custom": "com.atlassian.jira.plugin.system.customfieldtypes:select", "customId": 12312923}, "customfield_12312920": {"type": "string", "custom": "com.atlassian.jira.plugin.system.customfieldtypes:textfield", "customId": 12312920}, "customfield_12312921": {"type": "string", "custom": "com.atlassian.jira.plugin.system.customfieldtypes:textarea", "customId": 12312921}, "watches": {"type": "watches", "system": "watches"}, "created": {"type": "datetime", "system": "created"}, "customfield_12310192": {"type": "string", "custom": "com.atlassian.jira.plugin.system.customfieldtypes:textarea", "customId": 12310192}, "customfield_12310191": {"type": "array", "items": "option", "custom": "com.atlassian.jira.plugin.system.customfieldtypes:multicheckboxes", "customId": 12310191}, "customfield_12310230": {"type": "string", "custom": "com.atlassian.jira.plugin.system.customfieldtypes:textfield", "customId": 12310230}, "updated": {"type": "datetime", "system": "updated"}, "timeoriginalestimate": {"type": "number", "system": "timeoriginalestimate"}, "description": {"type": "string", "system": "description"}, "customfield_10010": {"type": "number", "custom": "com.atlassian.jira.plugin.system.customfieldtypes:importid", "customId": 10010}, "timetracking": {"type": "timetracking", "system": "timetracking"}, "customfield_12314523": {"type": "number", "custom": "com.atlassian.jpo:jpo-custom-field-original-story-points", "customId": 12314523}, "customfield_12314127": {"type": "string", "custom": "com.atlassian.jira.plugin.system.customfieldtypes:textarea", "customId": 12314127}, "customfield_12314522": {"type": "date", "custom": "com.atlassian.jpo:jpo-custom-field-baseline-end", "customId": 12314522}, "customfield_12314126": {"type": "array", "items": "version", "custom": "com.atlassian.jira.plugin.system.customfieldtypes:multiversion", "customId": 12314126}, "customfield_12314521": {"type": "date", "custom": "com.atlassian.jpo:jpo-custom-field-baseline-start", "customId": 12314521}, "customfield_12314125": {"type": "array", "items": "option", "custom": "com.atlassian.jira.plugin.system.customfieldtypes:multicheckboxes", "customId": 12314125}, "customfield_12310320": {"type": "array", "items": "version", "custom": "com.atlassian.jira.plugin.system.customfieldtypes:multiversion", "customId": 12310320}, "customfield_12314520": {"type": "any", "custom": "com.atlassian.jpo:jpo-custom-field-parent", "customId": 12314520}, "customfield_12314124": {"type": "array", "items": "option", "custom": "com.atlassian.jira.plugin.system.customfieldtypes:multicheckboxes", "customId": 12314124}, "customfield_12312340": {"type": "array", "items": "option", "custom": "com.atlassian.jira.plugin.system.customfieldtypes:multicheckboxes", "customId": 12312340}, "attachment": {"type": "array", "items": "attachment", "system": "attachment"}, "customfield_12314123": {"type": "string", "custom": "com.atlassian.jira.plugin.system.customfieldtypes:textarea", "customId": 12314123}, "customfield_12312341": {"type": "string", "custom": "com.atlassian.jira.plugin.system.customfieldtypes:textfield", "customId": 12312341}, "customfield_12312220": {"type": "option", "custom": "com.atlassian.jira.plugin.system.customfieldtypes:radiobuttons", "customId": 12312220}, "customfield_12314122": {"type": "number", "custom": "com.atlassian.jira.plugin.system.customfieldtypes:importid", "customId": 12314122}, "customfield_12314121": {"type": "option", "custom": "com.atlassian.jira.plugin.system.customfieldtypes:select", "customId": 12314121}, "customfield_12314120": {"type": "array", "items": "option", "custom": "com.atlassian.jira.plugin.system.customfieldtypes:multicheckboxes", "customId": 12314120}, "customfield_12314129": {"type": "date", "custom": "com.atlassian.jira.plugin.system.customfieldtypes:datepicker", "customId": 12314129}, "customfield_12314524": {"type": "any", "custom": "com.atlassian.teams:rm-teams-custom-field-team", "customId": 12314524}, "customfield_12314128": {"type": "string", "custom": "com.atlassian.jira.plugin.system.customfieldtypes:textarea", "customId": 12314128}, "summary": {"type": "string", "system": "summary"}, "customfield_12314130": {"type": "string", "custom": "com.atlassian.jira.plugin.system.customfieldtypes:textarea", "customId": 12314130}, "customfield_12310291": {"type": "array", "items": "string", "custom": "com.atlassian.jira.plugin.system.customfieldtypes:labels", "customId": 12310291}, "customfield_12310290": {"type": "array", "items": "option", "custom": "com.atlassian.jira.plugin.system.customfieldtypes:multicheckboxes", "customId": 12310290}, "customfield_12311024": {"type": "string", "custom": "com.atlassian.jira.plugin.system.customfieldtypes:textfield", "customId": 12311024}, "customfield_12314138": {"type": "array", "items": "version", "custom": "com.atlassian.jira.plugin.system.customfieldtypes:multiversion", "customId": 12314138}, "customfield_12314137": {"type": "string", "custom": "com.atlassian.jira.plugin.system.customfieldtypes:textfield", "customId": 12314137}, "environment": {"type": "string", "system": "environment"}, "customfield_12314136": {"type": "version", "custom": "com.atlassian.jira.plugin.system.customfieldtypes:version", "customId": 12314136}, "customfield_12314135": {"type": "user", "custom": "com.atlassian.jira.plugin.system.customfieldtypes:userpicker", "customId": 12314135}, "customfield_12311020": {"type": "string", "custom": "com.atlassian.jira.plugin.system.customfieldtypes:url", "customId": 12311020}, "customfield_12314134": {"type": "array", "items": "option", "custom": "com.atlassian.jira.plugin.system.customfieldtypes:multicheckboxes", "customId": 12314134}, "duedate": {"type": "date", "system": "duedate"}, "customfield_12314132": {"type": "array", "items": "option", "custom": "com.atlassian.jira.plugin.system.customfieldtypes:multicheckboxes", "customId": 12314132}, "customfield_12314131": {"type": "string", "custom": "com.atlassian.jira.plugin.system.customfieldtypes:textarea", "customId": 12314131}, "comment": {"type": "comments-page", "system": "comment"}, "customfield_12311820": {"type": "any", "custom": "com.pyxis.greenhopper.jira:gh-lexo-rank", "customId": 12311820}, "customfield_12314139": {"type": "user", "custom": "com.atlassian.jira.plugin.system.customfieldtypes:userpicker", "customId": 12314139}}}